{
  "logging":{
    "logInfo":true,
    "logWarnings":true,
    "logErrors":true
  },
  "debug":{
    "showInstrumentation":false
  },
  "cortexApi":{
    "path":"integrator",
    "scope":"cshop"
  },
  "deployMode":"development",
  "requireAuthToCheckout":true,
  "viewFadeInValue":500,
  "routes": {
    "newAddress":"#newaddressform",
    "cart":"#mycart",
    "category":"#category",
    "profile":"#profile",
    "itemDetail":"#itemdetail",
    "receipt": "#confirmation",
    "checkout" : "#checkout"
  }
}
